<?xml version='1.0'?>
<ns2:test-suite xmlns:ns2='urn:model.allure.qatools.yandex.ru' start='1634531023145' stop='1634531053260'>
    <name>Business rules</name>
    <title>Business rules</title>
    <test-cases>
        <test-case start='1634531023762' status='failed' stop='1634531039257'>
            <name>page @test</name>
            <title>page @test</title>
            <labels>
                <label name='tag' value='@test'/>
            </labels>
            <parameters/>
            <steps>
                <step start='1634531024360' status='passed' stop='1634531034312'>
                    <name>Given I have a defined step </name>
                    <title>Given I have a defined step </title>
                    <attachments/>
                    <steps>
                        <step start='1634531024360' status='passed' stop='1634531034312'>
                            <name>I am on page "/"</name>
                            <title>I am on page "/"</title>
                            <attachments>
                                <attachment title='Screenshot of step I am on page "/"' source='8836891f-d1aa-4453-a23d-6861b8ead863-attachment.png' type='image/png' size='1985854'/>
                            </attachments>
                            <steps/>
                        </step>
                    </steps>
                </step>
                <step start='1634531034313' status='failed' stop='1634531039257'>
                    <name>When i see youtube </name>
                    <title>When i see youtube </title>
                    <attachments/>
                    <steps>
                        <step start='1634531034313' status='failed' stop='1634531039254'>
                            <name>I see "logo", "id"</name>
                            <title>I see "logo", "id"</title>
                            <attachments/>
                            <steps/>
                        </step>
                    </steps>
                </step>
            </steps>
            <attachments>
                <attachment title='Screenshot of step I see "logo", "id"' source='98954b59-80c1-4928-8fe9-cec9f6d46679-attachment.png' type='image/png' size='4977867'/>
                <attachment title='Screenshot of step I wait 2' source='da591878-bfae-4153-b6a3-27a558757350-attachment.png' type='image/png' size='7140201'/>
                <attachment title='Last Seen Screenshot' source='f880fcdf-6360-4606-b66c-02c378aa3bfc-attachment.png' type='image/png' size='454653'/>
            </attachments>
            <failure>
                <message>Element "id" was not found by text|CSS|XPath</message>
                <stack-trace>Error: Element "id" was not found by text|CSS|XPath
                    at new ElementNotFound (E:\batch220\Automation\node_modules\codeceptjs\lib\helper\errors\ElementNotFound.js:14:11)
                    at assertElementExists (E:\batch220\Automation\node_modules\codeceptjs\lib\helper\Playwright.js:2630:11)
                    at Playwright.proceedSee (E:\batch220\Automation\node_modules\codeceptjs\lib\helper\Playwright.js:2438:5)</stack-trace>
            </failure>
        </test-case>
    </test-cases>
</ns2:test-suite>